schedule/__init__.py
schedule/api.py
schedule/structures.py
MySchedule.py-1.0.8.dist-info/LICENSE
MySchedule.py-1.0.8.dist-info/METADATA
MySchedule.py-1.0.8.dist-info/WHEEL
MySchedule.py-1.0.8.dist-info/top_level.txt
MySchedule.py-1.0.8.dist-info/RECORD
