Metadata-Version: 2.1
Name: MySchedule.py
Version: 1.0.8
Summary: A Python wrapper for the McDonalds Myschedule
Author: olijeffers0n
Author-email: pleaseUseMyDiscord@Please.com
License: MIT
Requires-Python: >=3.7.0
License-File: LICENSE
Requires-Dist: requests
Requires-Dist: datetime
Requires-Dist: bs4
Requires-Dist: pybase64
